alu-main/Adder/full_adder.v
module full_adder(S, A, B, Cin);
  input A, B, Cin;
  output S;
  wire w1, w2, w3;
    
  xor sum_result(S, A, B, Cin);
  and A_and_B(w1, A, B);
  and A_and_Cin(w2, A, Cin);
  and B_and_Cin(w3, B, Cin);
endmodule

alu-main/Adder/adder_8bit.v
module adder_8bit(Cin, A, B, sum, G, P);
  input Cin;
  input [7:0] A, B;
  output [7:0] sum;
  output G, P;

  wire [7:0] p;
  wire [7:0] g;
  wire w0, w1, w2, w3, w4, w5, w6;

  genvar i;
  for (i = 0; i < 8; i = i + 1) begin : gen_loop // calculate each pi and gi
    or p_results(p[i], A[i], B[i]);
    and g_results(g[i], A[i], B[i]);
  end

  and P0(P, p[7], p[6], p[5], p[4], p[3], p[2], p[1], p[0]); // calculates P0

  and first(w0, p[7], g[6]);
  and second(w1, p[7], p[6], g[5]);
  and third(w2, p[7], p[6], p[5], g[4]);
  and fourth(w3, p[7], p[6], p[5], p[4], g[3]);
  and fifth(w4, p[7], p[6], p[5], p[4], p[3], g[2]);
  and sixth(w5, p[7], p[6], p[5], p[4], p[3], p[2], g[1]);
  and seventh(w6, p[7], p[6], p[5], p[4], p[3], p[2], p[1], g[0]);

  or G0(G, g[7], w0, w1, w2, w3, w4, w5, w6); // calculates G0


  // calculate sums
  // 1st bit
  full_adder first_adder(sum[0], A[0], B[0], Cin);
  
  // 2nd bit
  wire carry_1, w7;
  and(w7, p[0], Cin);
  or carry_result1(carry_1, g[0], w7);
  full_adder second_adder(sum[1], A[1], B[1], carry_1);

  // 3rd bit
  wire carry_2, w8, w9;
  and(w8, p[1], g[0]);
  and(w9, p[1], p[0], Cin);
  or carry_result2(carry_2, g[1], w8, w9);
  full_adder third_adder(sum[2], A[2], B[2], carry_2);

  // 4th bit
  wire carry_3, w10, w11, w12;
  and(w10, p[2], g[1]);
  and(w11, p[2], p[1], g[0]);
  and(w12, p[2], p[1], p[0], Cin);
  or carry_result3(carry_3, g[2], w10, w11, w12);
  full_adder fourth_adder(sum[3], A[3], B[3], carry_3);

  // 5th bit
  wire carry_4, w13, w14, w15, w16;
  and(w13, p[3], g[2]);
  and(w14, p[3], p[2], g[1]);
  and(w15, p[3], p[2], p[1], g[0]);
  and(w16, p[3], p[2], p[1], p[0], Cin);
  or carry_result4(carry_4, g[3], w13, w14, w15, w16);
  full_adder fifth_adder(sum[4], A[4], B[4], carry_4);

  // 6th bit
  wire carry_5, w17, w18, w19, w20, w21;
  and(w17, p[4], g[3]);
  and(w18, p[4], p[3], g[2]);
  and(w19, p[4], p[3], p[2], g[1]);
  and(w20, p[4], p[3], p[2], p[1], g[0]);
  and(w21, p[4], p[3], p[2], p[1], p[0], Cin);
  or carry_result5(carry_5, g[4], w17, w18, w19, w20, w21);
  full_adder sixth_adder(sum[5], A[5], B[5], carry_5);

  // 7th bit
  wire carry_6, w22, w23, w24, w25, w26, w27;
  and(w22, p[5], g[4]);
  and(w23, p[5], p[4], g[3]);
  and(w24, p[5], p[4], p[3], g[2]);
  and(w25, p[5], p[4], p[3], p[2], g[1]);
  and(w26, p[5], p[4], p[3], p[2], p[1], g[0]);
  and(w27, p[5], p[4], p[3], p[2], p[1], p[0], Cin);
  or carry_result6(carry_6, g[5], w22, w23, w24, w25, w26, w27);
  full_adder seventh_adder(sum[6], A[6], B[6], carry_6);

  // 8th bit
  wire carry_7, w28, w29, w30, w31, w32, w33, w34;
  and(w28, p[6], g[5]);
  and(w29, p[6], p[5], g[4]);
  and(w30, p[6], p[5], p[4], g[3]);
  and(w31, p[6], p[5], p[4], p[3], g[2]);
  and(w32, p[6], p[5], p[4], p[3], p[2], g[1]);
  and(w33, p[6], p[5], p[4], p[3], p[2], p[1], g[0]);
  and(w34, p[6], p[5], p[4], p[3], p[2], p[1], p[0], Cin);
  or carry_result7(carry_7, g[6], w28, w29, w30, w31, w32, w33, w34);
  full_adder eighth_adder(sum[7], A[7], B[7], carry_7);
endmodule

alu-main/tests/adder_8bit_tb.v
`timescale 1 ns / 100 ps
module adder_8bit_tb;
  wire [7:0] A, B;
  reg Cin;
  reg a0, a1, a2, a3, a4, a5, a6, a7;
  reg b0, b1, b2, b3, b4, b5, b6, b7;

  wire G, P, Cout;
  wire [7:0] sum;
  adder_8bit adder(Cin, A, B, sum, G, P);

  wire w0;
  and carry8_1(w0, P, Cin);
  or carry8_2(Cout, G, w0);

  initial begin
    a0 = 0;
    a1 = 0;
    a2 = 0;
    a3 = 0;
    a4 = 0;
    a5 = 0;
    a6 = 0;
    a7 = 0;
    b0 = 0;
    b1 = 0;
    b2 = 0;
    b3 = 0;
    b4 = 0;
    b5 = 0;
    b6 = 0;
    b7 = 0;
    Cin = 0;
    #80; // time delay in ns
  end

  assign A[0] = a0;
  assign A[1] = a1;
  assign A[2] = a2;
  assign A[3] = a3;
  assign A[4] = a4;
  assign A[5] = a5;
  assign A[6] = a6;
  assign A[7] = a7;
  assign B[0] = b0;
  assign B[1] = b1;
  assign B[2] = b2;
  assign B[3] = b3;
  assign B[4] = b4;
  assign B[5] = b5;
  assign B[6] = b6;
  assign B[7] = b7;

  always
    #10 a0 = ~a0;
  always
    #20 a1 = ~a1;
  always 
    #40 a2 = ~a2;
  always
    #80 a3 = ~a3;
  always
    #160 a4 = ~a4;
  always
    #320 a5 = ~a5;
  always
    #640 a6 = ~a6;
  always
    #1280 a7 = ~a7;
  
  always
    #15 b0 = ~b0;
  always
    #30 b1 = ~b1;
  always
    #60 b2 = ~b2;
  always
    #120 b3 = ~b3;
  always
    #240 b4 = ~b4;
always
    #480 b5 = ~b5;
  always
    #960 b6 = ~b6;
  always
    #1920 b7 = ~b7;

  initial begin
    $dumpfile("adder_8bit_WaveForm.vcd");
    $dumpvars(0, adder_8bit_tb);
  end

  always @(A, B, sum, P, G, Cout) begin
    #1
    $display("%d + %d = %d", A, B, sum);
    if (Cout == 1)
      $finish;
  end
endmodule

alu-main/tests/adder_8bit_WaveForm.vcd
$date
	Tue Jan 31 21:46:43 2023
$end
$version
	Icarus Verilog
$end
$timescale
	100ps
$end
$scope module adder_8bit_tb $end
$var wire 8 ! sum [7:0] $end
$var wire 1 " P $end
$var wire 1 # G $end
$var wire 1 $ Cout $end
$var wire 8 % B [7:0] $end
$var wire 8 & A [7:0] $end
$var reg 1 ' Cin $end
$var reg 1 ( a0 $end
$var reg 1 ) a1 $end
$var reg 1 * a2 $end
$var reg 1 + a3 $end
$var reg 1 , a4 $end
$var reg 1 - a5 $end
$var reg 1 . a6 $end
$var reg 1 / a7 $end
$var reg 1 0 b0 $end
$var reg 1 1 b1 $end
$var reg 1 2 b2 $end
$var reg 1 3 b3 $end
$var reg 1 4 b4 $end
$var reg 1 5 b5 $end
$var reg 1 6 b6 $end
$var reg 1 7 b7 $end
$scope module adder $end
$var wire 8 8 A [7:0] $end
$var wire 8 9 B [7:0] $end
$var wire 1 ' Cin $end
$var wire 1 # G $end
$var wire 1 " P $end
$var wire 1 : carry_1 $end
$var wire 1 ; carry_2 $end
$var wire 1 < carry_3 $end
$var wire 1 = carry_4 $end
$var wire 1 > carry_5 $end
$var wire 1 ? carry_6 $end
$var wire 1 @ carry_7 $end
$var wire 1 A w0 $end
$var wire 1 B w1 $end
$var wire 1 C w10 $end
$var wire 1 D w11 $end
$var wire 1 E w12 $end
$var wire 1 F w13 $end
$var wire 1 G w14 $end
$var wire 1 H w15 $end
$var wire 1 I w16 $end
$var wire 1 J w17 $end
$var wire 1 K w18 $end
$var wire 1 L w19 $end
$var wire 1 M w2 $end
$var wire 1 N w20 $end
$var wire 1 O w21 $end
$var wire 1 P w22 $end
$var wire 1 Q w23 $end
$var wire 1 R w24 $end
$var wire 1 S w25 $end
$var wire 1 T w26 $end
$var wire 1 U w27 $end
$var wire 1 V w28 $end
$var wire 1 W w29 $end
$var wire 1 X w3 $end
$var wire 1 Y w30 $end
$var wire 1 Z w31 $end
$var wire 1 [ w32 $end
$var wire 1 \ w33 $end
$var wire 1 ] w34 $end
$var wire 1 ^ w4 $end
$var wire 1 _ w5 $end
$var wire 1 ` w6 $end
$var wire 1 a w7 $end
$var wire 1 b w8 $end
$var wire 1 c w9 $end
$var wire 8 d sum [7:0] $end
$var wire 8 e p [7:0] $end
$var wire 8 f g [7:0] $end
$scope begin gen_loop[0] $end
$var parameter 2 g i $end
$upscope $end
$scope begin gen_loop[1] $end
$var parameter 2 h i $end
$upscope $end
$scope begin gen_loop[2] $end
$var parameter 3 i i $end
$upscope $end
$scope begin gen_loop[3] $end
$var parameter 3 j i $end
$upscope $end
$scope begin gen_loop[4] $end
$var parameter 4 k i $end
$upscope $end
$scope begin gen_loop[5] $end
$var parameter 4 l i $end
$upscope $end
$scope begin gen_loop[6] $end
$var parameter 4 m i $end
$upscope $end
$scope begin gen_loop[7] $end
$var parameter 4 n i $end
$upscope $end
$scope module eighth_adder $end
$var wire 1 o A $end
$var wire 1 p B $end
$var wire 1 @ Cin $end
$var wire 1 q S $end
$var wire 1 r w1 $end
$var wire 1 s w2 $end
$var wire 1 t w3 $end
$upscope $end
$scope module fifth_adder $end
$var wire 1 u A $end
$var wire 1 v B $end
$var wire 1 = Cin $end
$var wire 1 w S $end
$var wire 1 x w1 $end
$var wire 1 y w2 $end
$var wire 1 z w3 $end
$upscope $end
$scope module first_adder $end
$var wire 1 { A $end
$var wire 1 | B $end
$var wire 1 ' Cin $end
$var wire 1 } S $end
$var wire 1 ~ w1 $end
$var wire 1 !" w2 $end
$var wire 1 "" w3 $end
$upscope $end
$scope module fourth_adder $end
$var wire 1 #" A $end
$var wire 1 $" B $end
$var wire 1 < Cin $end
$var wire 1 %" S $end
$var wire 1 &" w1 $end
$var wire 1 '" w2 $end
$var wire 1 (" w3 $end
$upscope $end
$scope module second_adder $end
$var wire 1 )" A $end
$var wire 1 *" B $end
$var wire 1 : Cin $end
$var wire 1 +" S $end
$var wire 1 ," w1 $end
$var wire 1 -" w2 $end
$var wire 1 ." w3 $end
$upscope $end
$scope module seventh_adder $end
$var wire 1 /" A $end
$var wire 1 0" B $end
$var wire 1 ? Cin $end
$var wire 1 1" S $end
$var wire 1 2" w1 $end
$var wire 1 3" w2 $end
$var wire 1 4" w3 $end
$upscope $end
$scope module sixth_adder $end
$var wire 1 5" A $end
$var wire 1 6" B $end
$var wire 1 > Cin $end
$var wire 1 7" S $end
$var wire 1 8" w1 $end
$var wire 1 9" w2 $end
$var wire 1 :" w3 $end
$upscope $end
$scope module third_adder $end
$var wire 1 ;" A $end
$var wire 1 <" B $end
$var wire 1 ; Cin $end
$var wire 1 =" S $end
$var wire 1 >" w1 $end
$var wire 1 ?" w2 $end
$var wire 1 @" w3 $end
$upscope $end
$upscope $end
$scope module cout $end
$var wire 1 ' Cin $end
$var wire 1 $ Cout $end
$var wire 1 # G $end
$var wire 1 " P $end
$var wire 1 A" w0 $end
$upscope $end
$upscope $end
$enddefinitions $end
$comment Show the parameter values. $end
$dumpall
b111 n
b110 m
b101 l
b100 k
b11 j
b10 i
b1 h
b0 g
$end
#0
$dumpvars
0A"
0@"
0?"
0>"
0="
0<"
0;"
0:"
09"
08"
07"
06"
05"
04"
03"
02"
01"
00"
0/"
0."
0-"
0,"
0+"
0*"
0)"
0("
0'"
0&"
0%"
0$"
0#"
0""
0!"
0~
0}
0|
0{
0z
0y
0x
0w
0v
0u
0t
0s
0r
0q
0p
0o
b0 f
b0 e
b0 d
0c
0b
0a
0`
0_
0^
0]
0\
0[
0Z
0Y
0X
0W
0V
0U
0T
0S
0R
0Q
0P
0O
0N
0M
0L
0K
0J
0I
0H
0G
0F
0E
0D
0C
0B
0A
0@
0?
0>
0=
0<
0;
0:
b0 9
b0 8
07
06
05
04
03
02
01
00
0/
0.
0-
0,
0+
0*
0)
0(
0'
b0 &
b0 %
0$
0#
0"
b0 !
$end
#100
b1 e
b1 !
b1 d
1}
1{
b1 &
b1 8
1(
#150
1+"
1:
b1 f
b10 !
b10 d
0}
1~
1|
b1 %
b1 9
10
#200
0:
b0 f
1}
0~
b11 e
b11 !
b11 d
1+"
0-"
0{
1)"
0(
b10 &
b10 8
1)
#300
1="
1;
b10 f
b101 !
b101 d
0+"
1,"
1{
0|
1*"
b11 &
b11 8
1(
00
b10 %
b10 9
11
#400
0;
0}
b0 f
1+"
0,"
b110 e
b110 !
b110 d
1="
0?"
0{
0)"
1;"
0(
0)
b100 &
b100 8
1*
#450
b111 e
b111 !
b111 d
1}
1|
b11 %
b11 9
10
#500
0="
1?"
1%"
0+"
1."
1;
1<
1:
1b
1D
b1 f
b1000 !
b1000 d
0}
1~
1{
b101 &
b101 8
1(
#600
0?"
1+"
0;
0:
0b
0D
b110 e
0~
0-"
0."
b100 f
b1010 !
b1010 d
0="
1>"
0@"
0{
0|
1)"
0*"
1<"
0(
00
b110 &
b110 8
1)
01
b100 %
b100 9
12
#700
b111 e
b1011 !
b1011 d
1}
1{
b111 &
b111 8
1(
#750
1="
1?"
1@"
0+"
1-"
1;
1:
1b
1D
b101 f
b1100 !
b1100 d
0}
1~
1|
b101 %
b101 9
10
#800
0@"
0;
0<
0:
0b
0D
1}
0~
0+"
0-"
b0 f
1="
0>"
0?"
b1101 e
b1101 !
b1101 d
1%"
0'"
0{
0)"
0;"
1#"
0(
0)
0*
b1000 &
b1000 8
1+
#900
b1111 e
b1111 !
b1111 d
1+"
1{
0|
1*"
b1001 &
b1001 8
1(
00
b110 %
b110 9
11
#1000
1w
0%"
1'"
1=
0="
1@"
1<
1;
1C
1G
b1110 e
0}
b10 f
b10000 !
b10000 d
0+"
1,"
0{
1)"
0(
b1010 &
b1010 8
1)
#1050
b1111 e
b10001 !
b10001 d
1}
1|
b111 %
b111 9
10
#1100
1+"
1-"
1."
1:
1b
1D
1H
b11 f
b10010 !
b10010 d
0}
1~
1{
b1011 &
b1011 8
1(
#1200
1="
0'"
0+"
0;
0<
0:
0b
0D
0H
0C
0G
0~
0-"
b1100 e
0,"
0."
0?"
0@"
b1000 f
b10100 !
b10100 d
0%"
1&"
0("
0{
0|
0)"
0*"
1;"
0<"
1$"
0(
00
0)
01
b1100 &
b1100 8
1*
02
b1000 %
b1000 9
13
#1300
b1101 e
b10101 !
b10101 d
1}
1{
b1101 &
b1101 8
1(
#1350
1+"
1:
b1001 f
b10110 !
b10110 d
0}
1~
1|
b1001 %
b1001 9
10
#1400
0:
b1000 f
1}
0~
b1111 e
b10111 !
b10111 d
1+"
0-"
0{
1)"
0(
b1110 &
b1110 8
1)
#1500
1%"
1'"
1("
0="
1?"
1<
1;
1C
1G
b1010 f
b11001 !
b11001 d
0+"
1,"
1{
0|
1*"
b1111 &
b1111 8
1(
00
b1010 %
b1010 9
11
#1600
0("
0=
0<
0;
0C
0G
0}
1+"
0,"
0="
0?"
b0 f
1%"
0&"
0'"
b11010 e
b11010 !
b11010 d
1w
0y
0{
0)"
0;"
0#"
1u
0(
0)
0*
0+
b10000 &
b10000 8
1,
#1650
b11011 e
b11011 !
b11011 d
1}
1|
b1011 %
b1011 9
10
#1700
1="
0+"
1."
1;
1:
1b
b1 f
b11100 !
b11100 d
0}
1~
1{
b10001 &
b10001 8
1(
#1800
1+"
0;
0:
0b
b0 f
0~
0-"
0."
b11110 e
b11110 !
b11110 d
1="
0@"
0{
0|
1)"
0*"
1<"
0(
00
b10010 &
b10010 8
1)
01
b1100 %
b1100 9
12
#1900
b11111 e
b11111 !
b11111 d
1}
1{
b10011 &
b10011 8
1(
#1950
17"
0w
1y
1>
0="
1@"
0%"
1("
1=
0+"
1-"
1;
1<
1N
1:
1b
1D
1H
b1 f
b100000 !
b100000 d
0}
1~
1|
b1101 %
b1101 9
10
#2000
0@"
0;
0N
0:
0b
0D
0H
1F
1K
1}
0~
b11101 e
0+"
0-"
b100 f
b100001 !
b100001 d
0="
1>"
0?"
0{
0)"
1;"
0(
0)
b10100 &
b10100 8
1*
#2100
b11111 e
b100011 !
b100011 d
1+"
1{
0|
1*"
b10101 &
b10101 8
1(
00
b1110 %
b1110 9
11
#2200
1="
1?"
1@"
1;
1C
1G
1L
b11110 e
0}
b110 f
b100100 !
b100100 d
0+"
1,"
0{
1)"
0(
b10110 &
b10110 8
1)
#2250
b11111 e
b100101 !
b100101 d
1}
1|
b1111 %
b1111 9
10
#2300
1+"
1-"
1."
1N
1:
1b
1D
1H
b111 f
b100110 !
b100110 d
0}
1~
1{
b10111 &
b10111 8
1(
#2400
0y
0="
1%"
0=
0+"
0;
0<
0N
0:
0b
0C
0D
0G
0H
0L
0F
0K
0~
0-"
0,"
0."
0?"
b11000 e
0>"
0@"
0'"
0("
b10000 f
b101000 !
b101000 d
0w
1x
0z
0{
0|
0)"
0*"
0;"
0<"
1#"
0$"
1v
0(
00
0)
01
0*
02
b11000 &
b11000 8
1+
03
b10000 %
b10000 9
14
#2500
b11001 e
b101001 !
b101001 d
1}
1{
b11001 &
b11001 8
1(
#2550
1+"
1:
b10001 f
b101010 !
b101010 d
0}
1~
1|
b10001 %
b10001 9
10
#2600
0:
b10000 f
1}
0~
b11011 e
b101011 !
b101011 d
1+"
0-"
0{
1)"
0(
b11010 &
b11010 8
1)
#2700
1="
1;
b10010 f
b101101 !
b101101 d
0+"
1,"
1{
0|
1*"
b11011 &
b11011 8
1(
00
b10010 %
b10010 9
11
#2800
0;
0}
b10000 f
1+"
0,"
b11110 e
b101110 !
b101110 d
1="
0?"
0{
0)"
1;"
0(
0)
b11100 &
b11100 8
1*
#2850
b11111 e
b101111 !
b101111 d
1}
1|
b10011 %
b10011 9
10
#2900
1w
1y
1z
0="
1?"
0%"
1'"
1=
0+"
1."
1;
1<
1N
1:
1b
1D
1H
b10001 f
b110000 !
b110000 d
0}
1~
1{
b11101 &
b11101 8
1(
#3000
0?"
1+"
0;
0N
0:
0b
0D
0H
1F
1K
b11110 e
0~
0-"
0."
b10100 f
b110010 !
b110010 d
0="
1>"
0@"
0{
0|
1)"
0*"
1<"
0(
00
b11110 &
b11110 8
1)
01
b10100 %
b10100 9
12
#3100
b11111 e
b110011 !
b110011 d
1}
1{
b11111 &
b11111 8
1(
#3150
1="
1?"
1@"
0+"
1-"
1;
1N
1:
1b
1D
1H
b10101 f
b110100 !
b110100 d
0}
1~
1|
b10101 %
b10101 9
10
#3200
0z
0@"
0=
0>
0;
0<
0N
0:
0b
0D
0F
0H
0K
1}
0~
0+"
0-"
1="
0>"
0?"
0%"
0'"
b0 f
1w
0x
0y
b110101 e
b110101 !
b110101 d
17"
09"
0{
0)"
0;"
0#"
0u
15"
0(
0)
0*
0+
0,
b100000 &
b100000 8
1-
#3300
b110111 e
b110111 !
b110111 d
1+"
1{
0|
1*"
b100001 &
b100001 8
1(
00
b10110 %
b10110 9
11
#3400
1%"
0="
1@"
1<
1;
1C
b110110 e
0}
b10 f
b111000 !
b111000 d
0+"
1,"
0{
1)"
0(
b100010 &
b100010 8
1)
#3450
b110111 e
b111001 !
b111001 d
1}
1|
b10111 %
b10111 9
10
#3500
1+"
1-"
1."
1:
1b
1D
b11 f
b111010 !
b111010 d
0}
1~
1{
b100011 &
b100011 8
1(
#3600
1="
0+"
0;
0<
0:
0b
0D
0C
0~
0-"
b0 f
0,"
0."
0?"
0@"
b111100 e
b111100 !
b111100 d
1%"
0("
0{
0|
0)"
0*"
1;"
0<"
1$"
0(
00
0)
01
b100100 &
b100100 8
1*
02
b11000 %
b11000 9
13
#3700
b111101 e
b111101 !
b111101 d
1}
1{
b100101 &
b100101 8
1(
#3750
1+"
1:
b1 f
b111110 !
b111110 d
0}
1~
1|
b11001 %
b11001 9
10
#3800
0:
b0 f
1}
0~
b111111 e
b111111 !
b111111 d
1+"
0-"
0{
1)"
0(
b100110 &
b100110 8
1)
#3900
11"
0w
1z
07"
19"
1?
0%"
1("
1=
1>
0="
1?"
1<
1S
1;
1C
1G
1L
b10 f
b1000001 !
b1000001 d
0+"
1,"
1{
0|
1*"
b100111 &
b100111 8
1(
00
b11010 %
b11010 9
11
#4000
0("
0<
0S
0;
0C
0G
0L
1J
1Q
0}
1+"
0,"
b111010 e
0="
0?"
b1000 f
b1000010 !
b1000010 d
0%"
1&"
0'"
0{
0)"
0;"
1#"
0(
0)
0*
b101000 &
b101000 8
1+
#4050
b111011 e
b1000011 !
b1000011 d
1}
1|
b11011 %
b11011 9
10
#4100
1="
0+"
1."
1;
1:
1b
b1001 f
b1000100 !
b1000100 d
0}
1~
1{
b101001 &
b101001 8
1(
#4200
1+"
0;
0:
0b
b1000 f
0~
0-"
0."
b111110 e
b1000110 !
b1000110 d
1="
0@"
0{
0|
1)"
0*"
1<"
0(
00
b101010 &
b101010 8
1)
01
b11100 %
b11100 9
12
#4300
b111111 e
b1000111 !
b1000111 d
1}
1{
b101011 &
b101011 8
1(
#4350
0="
1@"
1%"
1'"
1("
0+"
1-"
1;
1<
1N
1T
1:
1b
1D
1H
b1001 f
b1001000 !
b1001000 d
0}
1~
1|
b11101 %
b11101 9
10
#4400
0@"
0;
0N
0T
0:
0b
0D
0H
1F
1K
1R
1}
0~
b111101 e
0+"
0-"
b1100 f
b1001001 !
b1001001 d
0="
1>"
0?"
0{
0)"
1;"
0(
0)
b101100 &
b101100 8
1*
#4500
b111111 e
b1001011 !
b1001011 d
1+"
1{
0|
1*"
b101101 &
b101101 8
1(
00
b11110 %
b11110 9
11
#4600
1="
1?"
1@"
1S
1;
1C
1G
1L
b111110 e
0}
b1110 f
b1001100 !
b1001100 d
0+"
1,"
0{
1)"
0(
b101110 &
b101110 8
1)
#4650
b111111 e
b1001101 !
b1001101 d
1}
1|
b11111 %
b11111 9
10
#4700
1+"
1-"
1."
1N
1T
1:
1b
1D
1H
b1111 f
b1001110 !
b1001110 d
0}
1~
1{
b101111 &
b101111 8
1(
#4800
09"
1w
0>
0="
0%"
0=
0+"
0;
0<
0N
0S
0T
0:
0b
0C
0D
0F
0G
0H
0K
0L
0R
0J
0Q
0~
0-"
0,"
0."
0?"
0>"
0@"
0'"
b110000 e
0&"
0("
0y
0z
b100000 f
b1010000 !
b1010000 d
07"
18"
0:"
0{
0|
0)"
0*"
0;"
0<"
0#"
0$"
1u
0v
16"
0(
00
0)
01
0*
02
0+
03
b110000 &
b110000 8
1,
04
b100000 %
b100000 9
15
#4900
b110001 e
b1010001 !
b1010001 d
1}
1{
b110001 &
b110001 8
1(
#4950
1+"
1:
b100001 f
b1010010 !
b1010010 d
0}
1~
1|
b100001 %
b100001 9
10
#5000
0:
b100000 f
1}
0~
b110011 e
b1010011 !
b1010011 d
1+"
0-"
0{
1)"
0(
b110010 &
b110010 8
1)
#5100
1="
1;
b100010 f
b1010101 !
b1010101 d
0+"
1,"
1{
0|
1*"
b110011 &
b110011 8
1(
00
b100010 %
b100010 9
11
#5200
0;
0}
b100000 f
1+"
0,"
b110110 e
b1010110 !
b1010110 d
1="
0?"
0{
0)"
1;"
0(
0)
b110100 &
b110100 8
1*
#5250
b110111 e
b1010111 !
b1010111 d
1}
1|
b100011 %
b100011 9
10
#5300
0="
1?"
1%"
0+"
1."
1;
1<
1:
1b
1D
b100001 f
b1011000 !
b1011000 d
0}
1~
1{
b110101 &
b110101 8
1(
#5400
0?"
1+"
0;
0:
0b
0D
b110110 e
0~
0-"
0."
b100100 f
b1011010 !
b1011010 d
0="
1>"
0@"
0{
0|
1)"
0*"
1<"
0(
00
b110110 &
b110110 8
1)
01
b100100 %
b100100 9
12
#5500
b110111 e
b1011011 !
b1011011 d
1}
1{
b110111 &
b110111 8
1(
#5550
1="
1?"
1@"
0+"
1-"
1;
1:
1b
1D
b100101 f
b1011100 !
b1011100 d
0}
1~
1|
b100101 %
b100101 9
10
#5600
0@"
0;
0<
0:
0b
0D
1}
0~
0+"
0-"
b100000 f
1="
0>"
0?"
b111101 e
b1011101 !
b1011101 d
1%"
0'"
0{
0)"
0;"
1#"
0(
0)
0*
b111000 &
b111000 8
1+
#5700
b111111 e
b1011111 !
b1011111 d
1+"
1{
0|
1*"
b111001 &
b111001 8
1(
00
b100110 %
b100110 9
11
#5800
0w
1y
17"
19"
1:"
0%"
1'"
1=
1>
0="
1@"
1<
1S
1;
1C
1G
1L
b111110 e
0}
b100010 f
b1100000 !
b1100000 d
0+"
1,"
0{
1)"
0(
b111010 &
b111010 8
1)
#5850
b111111 e
b1100001 !
b1100001 d
1}
1|
b100111 %
b100111 9
10
#5900
1+"
1-"
1."
1N
1T
1:
1b
1D
1H
b100011 f
b1100010 !
b1100010 d
0}
1~
1{
b111011 &
b111011 8
1(
#6000
1="
0'"
0+"
0;
0N
0T
0<
0S
0:
0b
0D
0H
0C
0G
0L
1J
1Q
0~
0-"
b111100 e
0,"
0."
0?"
0@"
b101000 f
b1100100 !
b1100100 d
0%"
1&"
0("
0{
0|
0)"
0*"
1;"
0<"
1$"
0(
00
0)
01
b111100 &
b111100 8
1*
02
b101000 %
b101000 9
13
#6100
b111101 e
b1100101 !
b1100101 d
1}
1{
b111101 &
b111101 8
1(
#6150
1+"
1:
b101001 f
b1100110 !
b1100110 d
0}
1~
1|
b101001 %
b101001 9
10
#6200
0:
b101000 f
1}
0~
b111111 e
b1100111 !
b1100111 d
1+"
0-"
0{
1)"
0(
b111110 &
b111110 8
1)
#6300
1%"
1'"
1("
0="
1?"
1<
1S
1;
1C
1G
1L
b101010 f
b1101001 !
b1101001 d
0+"
1,"
1{
0|
1*"
b111111 &
b111111 8
1(
00
b101010 %
b101010 9
11
#6400
0:"
0("
0=
0>
0?
0<
0S
0;
0C
0G
0J
0L
0Q
0}
1+"
0,"
0="
0?"
1%"
0&"
0'"
0w
0y
b0 f
17"
08"
09"
b1101010 e
b1101010 !
b1101010 d
11"
03"
0{
0)"
0;"
0#"
0u
05"
1/"
0(
0)
0*
0+
0,
0-
b1000000 &
b1000000 8
1.
#6450
b1101011 e
b1101011 !
b1101011 d
1}
1|
b101011 %
b101011 9
10
#6500
1="
0+"
1."
1;
1:
1b
b1 f
b1101100 !
b1101100 d
0}
1~
1{
b1000001 &
b1000001 8
1(
#6600
1+"
0;
0:
0b
b0 f
0~
0-"
0."
b1101110 e
b1101110 !
b1101110 d
1="
0@"
0{
0|
1)"
0*"
1<"
0(
00
b1000010 &
b1000010 8
1)
01
b101100 %
b101100 9
12
#6700
b1101111 e
b1101111 !
b1101111 d
1}
1{
b1000011 &
b1000011 8
1(
#6750
1w
0="
1@"
0%"
1("
1=
0+"
1-"
1;
1<
1:
1b
1D
1H
b1 f
b1110000 !
b1110000 d
0}
1~
1|
b101101 %
b101101 9
10
#6800
0@"
0;
0:
0b
0D
0H
1F
1}
0~
b1101101 e
0+"
0-"
b100 f
b1110001 !
b1110001 d
0="
1>"
0?"
0{
0)"
1;"
0(
0)
b1000100 &
b1000100 8
1*
#6900
b1101111 e
b1110011 !
b1110011 d
1+"
1{
0|
1*"
b1000101 &
b1000101 8
1(
00
b101110 %
b101110 9
11
#7000
1="
1?"
1@"
1;
1C
1G
b1101110 e
0}
b110 f
b1110100 !
b1110100 d
0+"
1,"
0{
1)"
0(
b1000110 &
b1000110 8
1)
#7050
b1101111 e
b1110101 !
b1110101 d
1}
1|
b101111 %
b101111 9
10
#7100
1+"
1-"
1."
1:
1b
1D
1H
b111 f
b1110110 !
b1110110 d
0}
1~
1{
b1000111 &
b1000111 8
1(
#7200
0="
1%"
0=
0+"
0;
0<
0:
0b
0C
0D
0G
0H
0F
0~
0-"
0,"
0."
0?"
b0 f
0>"
0@"
0'"
0("
b1111000 e
b1111000 !
b1111000 d
1w
0z
0{
0|
0)"
0*"
0;"
0<"
1#"
0$"
1v
0(
00
0)
01
0*
02
b1001000 &
b1001000 8
1+
03
b110000 %
b110000 9
14
#7300
b1111001 e
b1111001 !
b1111001 d
1}
1{
b1001001 &
b1001001 8
1(
#7350
1+"
1:
b1 f
b1111010 !
b1111010 d
0}
1~
1|
b110001 %
b110001 9
10
#7400
0:
b0 f
1}
0~
b1111011 e
b1111011 !
b1111011 d
1+"
0-"
0{
1)"
0(
b1001010 &
b1001010 8
1)
#7500
1="
1;
b10 f
b1111101 !
b1111101 d
0+"
1,"
1{
0|
1*"
b1001011 &
b1001011 8
1(
00
b110010 %
b110010 9
11
#7600
0;
0}
b0 f
1+"
0,"
b1111110 e
b1111110 !
b1111110 d
1="
0?"
0{
0)"
1;"
0(
0)
b1001100 &
b1001100 8
1*
#7650
b1111111 e
b1111111 !
b1111111 d
1}
1|
b110011 %
b110011 9
10
#7700
07"
1:"
01"
13"
1q
0w
1z
1>
1?
1@
0="
1?"
0%"
1'"
1=
0+"
1."
1;
1<
1N
1T
1\
1:
1b
1D
1H
b1 f
b10000000 !
b10000000 d
0}
1~
1{
b1001101 &
b1001101 8
1(
#7800
0?"
1+"
0;
0N
0T
0\
1Z
0:
0b
0D
0H
1F
1K
1R
b1111110 e
0~
0-"
0."
b100 f
b10000010 !
b10000010 d
0="
1>"
0@"
0{
0|
1)"
0*"
1<"
0(
00
b1001110 &
b1001110 8
1)
01
b110100 %
b110100 9
12
#7900
b1111111 e
b10000011 !
b10000011 d
1}
1{
b1001111 &
b1001111 8
1(
#7950
1="
1?"
1@"
0+"
1-"
1;
1N
1T
1\
1:
1b
1D
1H
b101 f
b10000100 !
b10000100 d
0}
1~
1|
b110101 %
b110101 9
10
#8000
0z
0@"
0=
0;
0<
0N
0T
0Z
0\
0:
0b
0D
0F
0H
0K
0R
1P
1W
1}
0~
0+"
0-"
1="
0>"
0?"
b1110101 e
0%"
0'"
b10000 f
b10000101 !
b10000101 d
0w
1x
0y
0{
0)"
0;"
0#"
1u
0(
0)
0*
0+
b1010000 &
b1010000 8
1,
#8100
b1110111 e
b10000111 !
b10000111 d
1+"
1{
0|
1*"
b1010001 &
b1010001 8
1(
00
b110110 %
b110110 9
11
